demos/__init__.py
lazy/__init__.py
lazy/datetime.py
st_lazys-0.2.dist-info/LICENSE
st_lazys-0.2.dist-info/METADATA
st_lazys-0.2.dist-info/WHEEL
st_lazys-0.2.dist-info/top_level.txt
st_lazys-0.2.dist-info/RECORD
