Metadata-Version: 2.1
Name: st-lazys
Version: 0.2
Summary: 一个非常NB的包
Home-page: UNKNOWN
Author: songtao
Author-email: 
License: UNKNOWN
Platform: UNKNOWN
Classifier: Programming Language :: Python :: 3
Classifier: License :: OSI Approved :: MIT License
Classifier: Operating System :: OS Independent
Requires-Python: >=3
License-File: LICENSE
Requires-Dist: requests
